[
  {
    "name": null,
    "methods": [
      "POST"
    ],
    "paramNames": [],
    "path": "/admin/login",
    "regexp": "/^\\/admin\\/login(?:\\/(?=$))?$/",
    "stack": [
      "wrappedController"
    ]
  },
  {
    "name": null,
    "methods": [
      "HEAD",
      "GET"
    ],
    "paramNames": [],
    "path": "/admin/info",
    "regexp": "/^\\/admin\\/info(?:\\/(?=$))?$/",
    "stack": [
      "middleware",
      "wrappedController"
    ]
  },
  {
    "name": null,
    "methods": [
      "POST"
    ],
    "paramNames": [],
    "path": "/admin/upload",
    "regexp": "/^\\/admin\\/upload(?:\\/(?=$))?$/",
    "stack": [
      "middleware",
      "wrappedController"
    ]
  },
  {
    "name": null,
    "methods": [
      "DELETE"
    ],
    "paramNames": [],
    "path": "/admin/upload",
    "regexp": "/^\\/admin\\/upload(?:\\/(?=$))?$/",
    "stack": [
      "middleware",
      "wrappedController"
    ]
  },
  {
    "name": "s",
    "methods": [
      "HEAD",
      "GET"
    ],
    "paramNames": [],
    "path": "/admin/user",
    "regexp": "/^\\/admin\\/user(?:\\/(?=$))?$/",
    "stack": [
      "middleware",
      "wrappedController"
    ]
  },
  {
    "name": "s",
    "methods": [
      "POST"
    ],
    "paramNames": [],
    "path": "/admin/user",
    "regexp": "/^\\/admin\\/user(?:\\/(?=$))?$/",
    "stack": [
      "middleware",
      "wrappedController"
    ]
  },
  {
    "name": null,
    "methods": [
      "HEAD",
      "GET"
    ],
    "paramNames": [
      {
        "name": "id",
        "prefix": "/",
        "delimiter": "/",
        "optional": false,
        "repeat": false,
        "partial": false,
        "asterisk": false,
        "pattern": "[^\\/]+?"
      }
    ],
    "path": "/admin/user/:id",
    "regexp": "/^\\/admin\\/user\\/((?:[^\\/]+?))(?:\\/(?=$))?$/",
    "stack": [
      "middleware",
      "wrappedController"
    ]
  },
  {
    "name": null,
    "methods": [
      "PATCH",
      "PUT"
    ],
    "paramNames": [
      {
        "name": "id",
        "prefix": "/",
        "delimiter": "/",
        "optional": false,
        "repeat": false,
        "partial": false,
        "asterisk": false,
        "pattern": "[^\\/]+?"
      }
    ],
    "path": "/admin/user/:id",
    "regexp": "/^\\/admin\\/user\\/((?:[^\\/]+?))(?:\\/(?=$))?$/",
    "stack": [
      "middleware",
      "wrappedController"
    ]
  },
  {
    "name": "destroy_",
    "methods": [
      "DELETE"
    ],
    "paramNames": [
      {
        "name": "id",
        "prefix": "/",
        "delimiter": "/",
        "optional": false,
        "repeat": false,
        "partial": false,
        "asterisk": false,
        "pattern": "[^\\/]+?"
      }
    ],
    "path": "/admin/user/:id",
    "regexp": "/^\\/admin\\/user\\/((?:[^\\/]+?))(?:\\/(?=$))?$/",
    "stack": [
      "middleware",
      "wrappedController"
    ]
  },
  {
    "name": null,
    "methods": [
      "DELETE"
    ],
    "paramNames": [],
    "path": "/admin/user",
    "regexp": "/^\\/admin\\/user(?:\\/(?=$))?$/",
    "stack": [
      "middleware",
      "wrappedController"
    ]
  },
  {
    "name": "s",
    "methods": [
      "HEAD",
      "GET"
    ],
    "paramNames": [],
    "path": "/admin/menu",
    "regexp": "/^\\/admin\\/menu(?:\\/(?=$))?$/",
    "stack": [
      "middleware",
      "wrappedController"
    ]
  },
  {
    "name": "s",
    "methods": [
      "POST"
    ],
    "paramNames": [],
    "path": "/admin/menu",
    "regexp": "/^\\/admin\\/menu(?:\\/(?=$))?$/",
    "stack": [
      "middleware",
      "wrappedController"
    ]
  },
  {
    "name": null,
    "methods": [
      "PATCH",
      "PUT"
    ],
    "paramNames": [
      {
        "name": "id",
        "prefix": "/",
        "delimiter": "/",
        "optional": false,
        "repeat": false,
        "partial": false,
        "asterisk": false,
        "pattern": "[^\\/]+?"
      }
    ],
    "path": "/admin/menu/:id",
    "regexp": "/^\\/admin\\/menu\\/((?:[^\\/]+?))(?:\\/(?=$))?$/",
    "stack": [
      "middleware",
      "wrappedController"
    ]
  },
  {
    "name": "destroy_",
    "methods": [
      "DELETE"
    ],
    "paramNames": [
      {
        "name": "id",
        "prefix": "/",
        "delimiter": "/",
        "optional": false,
        "repeat": false,
        "partial": false,
        "asterisk": false,
        "pattern": "[^\\/]+?"
      }
    ],
    "path": "/admin/menu/:id",
    "regexp": "/^\\/admin\\/menu\\/((?:[^\\/]+?))(?:\\/(?=$))?$/",
    "stack": [
      "middleware",
      "wrappedController"
    ]
  },
  {
    "name": null,
    "methods": [
      "POST"
    ],
    "paramNames": [],
    "path": "/admin/menu/sort",
    "regexp": "/^\\/admin\\/menu\\/sort(?:\\/(?=$))?$/",
    "stack": [
      "middleware",
      "wrappedController"
    ]
  },
  {
    "name": "s",
    "methods": [
      "HEAD",
      "GET"
    ],
    "paramNames": [],
    "path": "/admin/role",
    "regexp": "/^\\/admin\\/role(?:\\/(?=$))?$/",
    "stack": [
      "middleware",
      "wrappedController"
    ]
  },
  {
    "name": "s",
    "methods": [
      "POST"
    ],
    "paramNames": [],
    "path": "/admin/role",
    "regexp": "/^\\/admin\\/role(?:\\/(?=$))?$/",
    "stack": [
      "middleware",
      "wrappedController"
    ]
  },
  {
    "name": null,
    "methods": [
      "PATCH",
      "PUT"
    ],
    "paramNames": [
      {
        "name": "id",
        "prefix": "/",
        "delimiter": "/",
        "optional": false,
        "repeat": false,
        "partial": false,
        "asterisk": false,
        "pattern": "[^\\/]+?"
      }
    ],
    "path": "/admin/role/:id",
    "regexp": "/^\\/admin\\/role\\/((?:[^\\/]+?))(?:\\/(?=$))?$/",
    "stack": [
      "middleware",
      "wrappedController"
    ]
  },
  {
    "name": "destroy_",
    "methods": [
      "DELETE"
    ],
    "paramNames": [
      {
        "name": "id",
        "prefix": "/",
        "delimiter": "/",
        "optional": false,
        "repeat": false,
        "partial": false,
        "asterisk": false,
        "pattern": "[^\\/]+?"
      }
    ],
    "path": "/admin/role/:id",
    "regexp": "/^\\/admin\\/role\\/((?:[^\\/]+?))(?:\\/(?=$))?$/",
    "stack": [
      "middleware",
      "wrappedController"
    ]
  },
  {
    "name": null,
    "methods": [
      "DELETE"
    ],
    "paramNames": [],
    "path": "/admin/role",
    "regexp": "/^\\/admin\\/role(?:\\/(?=$))?$/",
    "stack": [
      "middleware",
      "wrappedController"
    ]
  },
  {
    "name": "s",
    "methods": [
      "HEAD",
      "GET"
    ],
    "paramNames": [],
    "path": "/admin/wxUser",
    "regexp": "/^\\/admin\\/wxUser(?:\\/(?=$))?$/",
    "stack": [
      "middleware",
      "wrappedController"
    ]
  },
  {
    "name": "destroy_",
    "methods": [
      "DELETE"
    ],
    "paramNames": [
      {
        "name": "id",
        "prefix": "/",
        "delimiter": "/",
        "optional": false,
        "repeat": false,
        "partial": false,
        "asterisk": false,
        "pattern": "[^\\/]+?"
      }
    ],
    "path": "/admin/wxUser/:id",
    "regexp": "/^\\/admin\\/wxUser\\/((?:[^\\/]+?))(?:\\/(?=$))?$/",
    "stack": [
      "middleware",
      "wrappedController"
    ]
  },
  {
    "name": null,
    "methods": [
      "DELETE"
    ],
    "paramNames": [],
    "path": "/admin/wxUser",
    "regexp": "/^\\/admin\\/wxUser(?:\\/(?=$))?$/",
    "stack": [
      "middleware",
      "wrappedController"
    ]
  },
  {
    "name": "s",
    "methods": [
      "HEAD",
      "GET"
    ],
    "paramNames": [],
    "path": "/admin/category",
    "regexp": "/^\\/admin\\/category(?:\\/(?=$))?$/",
    "stack": [
      "middleware",
      "wrappedController"
    ]
  },
  {
    "name": "s",
    "methods": [
      "POST"
    ],
    "paramNames": [],
    "path": "/admin/category",
    "regexp": "/^\\/admin\\/category(?:\\/(?=$))?$/",
    "stack": [
      "middleware",
      "wrappedController"
    ]
  },
  {
    "name": null,
    "methods": [
      "PATCH",
      "PUT"
    ],
    "paramNames": [
      {
        "name": "id",
        "prefix": "/",
        "delimiter": "/",
        "optional": false,
        "repeat": false,
        "partial": false,
        "asterisk": false,
        "pattern": "[^\\/]+?"
      }
    ],
    "path": "/admin/category/:id",
    "regexp": "/^\\/admin\\/category\\/((?:[^\\/]+?))(?:\\/(?=$))?$/",
    "stack": [
      "middleware",
      "wrappedController"
    ]
  },
  {
    "name": "destroy_",
    "methods": [
      "DELETE"
    ],
    "paramNames": [
      {
        "name": "id",
        "prefix": "/",
        "delimiter": "/",
        "optional": false,
        "repeat": false,
        "partial": false,
        "asterisk": false,
        "pattern": "[^\\/]+?"
      }
    ],
    "path": "/admin/category/:id",
    "regexp": "/^\\/admin\\/category\\/((?:[^\\/]+?))(?:\\/(?=$))?$/",
    "stack": [
      "middleware",
      "wrappedController"
    ]
  },
  {
    "name": null,
    "methods": [
      "DELETE"
    ],
    "paramNames": [],
    "path": "/admin/category",
    "regexp": "/^\\/admin\\/category(?:\\/(?=$))?$/",
    "stack": [
      "middleware",
      "wrappedController"
    ]
  },
  {
    "name": null,
    "methods": [
      "POST"
    ],
    "paramNames": [],
    "path": "/admin/category/sort",
    "regexp": "/^\\/admin\\/category\\/sort(?:\\/(?=$))?$/",
    "stack": [
      "middleware",
      "wrappedController"
    ]
  },
  {
    "name": "s",
    "methods": [
      "HEAD",
      "GET"
    ],
    "paramNames": [],
    "path": "/admin/goods",
    "regexp": "/^\\/admin\\/goods(?:\\/(?=$))?$/",
    "stack": [
      "middleware",
      "wrappedController"
    ]
  },
  {
    "name": "s",
    "methods": [
      "POST"
    ],
    "paramNames": [],
    "path": "/admin/goods",
    "regexp": "/^\\/admin\\/goods(?:\\/(?=$))?$/",
    "stack": [
      "middleware",
      "wrappedController"
    ]
  },
  {
    "name": null,
    "methods": [
      "HEAD",
      "GET"
    ],
    "paramNames": [
      {
        "name": "id",
        "prefix": "/",
        "delimiter": "/",
        "optional": false,
        "repeat": false,
        "partial": false,
        "asterisk": false,
        "pattern": "[^\\/]+?"
      }
    ],
    "path": "/admin/goods/:id",
    "regexp": "/^\\/admin\\/goods\\/((?:[^\\/]+?))(?:\\/(?=$))?$/",
    "stack": [
      "middleware",
      "wrappedController"
    ]
  },
  {
    "name": null,
    "methods": [
      "PATCH",
      "PUT"
    ],
    "paramNames": [
      {
        "name": "id",
        "prefix": "/",
        "delimiter": "/",
        "optional": false,
        "repeat": false,
        "partial": false,
        "asterisk": false,
        "pattern": "[^\\/]+?"
      }
    ],
    "path": "/admin/goods/:id",
    "regexp": "/^\\/admin\\/goods\\/((?:[^\\/]+?))(?:\\/(?=$))?$/",
    "stack": [
      "middleware",
      "wrappedController"
    ]
  },
  {
    "name": "destroy_",
    "methods": [
      "DELETE"
    ],
    "paramNames": [
      {
        "name": "id",
        "prefix": "/",
        "delimiter": "/",
        "optional": false,
        "repeat": false,
        "partial": false,
        "asterisk": false,
        "pattern": "[^\\/]+?"
      }
    ],
    "path": "/admin/goods/:id",
    "regexp": "/^\\/admin\\/goods\\/((?:[^\\/]+?))(?:\\/(?=$))?$/",
    "stack": [
      "middleware",
      "wrappedController"
    ]
  },
  {
    "name": null,
    "methods": [
      "DELETE"
    ],
    "paramNames": [],
    "path": "/admin/goods",
    "regexp": "/^\\/admin\\/goods(?:\\/(?=$))?$/",
    "stack": [
      "middleware",
      "wrappedController"
    ]
  },
  {
    "name": "s",
    "methods": [
      "HEAD",
      "GET"
    ],
    "paramNames": [],
    "path": "/admin/banner",
    "regexp": "/^\\/admin\\/banner(?:\\/(?=$))?$/",
    "stack": [
      "middleware",
      "wrappedController"
    ]
  },
  {
    "name": "s",
    "methods": [
      "POST"
    ],
    "paramNames": [],
    "path": "/admin/banner",
    "regexp": "/^\\/admin\\/banner(?:\\/(?=$))?$/",
    "stack": [
      "middleware",
      "wrappedController"
    ]
  },
  {
    "name": null,
    "methods": [
      "PATCH",
      "PUT"
    ],
    "paramNames": [
      {
        "name": "id",
        "prefix": "/",
        "delimiter": "/",
        "optional": false,
        "repeat": false,
        "partial": false,
        "asterisk": false,
        "pattern": "[^\\/]+?"
      }
    ],
    "path": "/admin/banner/:id",
    "regexp": "/^\\/admin\\/banner\\/((?:[^\\/]+?))(?:\\/(?=$))?$/",
    "stack": [
      "middleware",
      "wrappedController"
    ]
  },
  {
    "name": "destroy_",
    "methods": [
      "DELETE"
    ],
    "paramNames": [
      {
        "name": "id",
        "prefix": "/",
        "delimiter": "/",
        "optional": false,
        "repeat": false,
        "partial": false,
        "asterisk": false,
        "pattern": "[^\\/]+?"
      }
    ],
    "path": "/admin/banner/:id",
    "regexp": "/^\\/admin\\/banner\\/((?:[^\\/]+?))(?:\\/(?=$))?$/",
    "stack": [
      "middleware",
      "wrappedController"
    ]
  },
  {
    "name": null,
    "methods": [
      "DELETE"
    ],
    "paramNames": [],
    "path": "/admin/banner",
    "regexp": "/^\\/admin\\/banner(?:\\/(?=$))?$/",
    "stack": [
      "middleware",
      "wrappedController"
    ]
  },
  {
    "name": null,
    "methods": [
      "POST"
    ],
    "paramNames": [],
    "path": "/admin/banner/sort",
    "regexp": "/^\\/admin\\/banner\\/sort(?:\\/(?=$))?$/",
    "stack": [
      "middleware",
      "wrappedController"
    ]
  },
  {
    "name": "s",
    "methods": [
      "HEAD",
      "GET"
    ],
    "paramNames": [],
    "path": "/admin/home_nav",
    "regexp": "/^\\/admin\\/home_nav(?:\\/(?=$))?$/",
    "stack": [
      "middleware",
      "wrappedController"
    ]
  },
  {
    "name": "s",
    "methods": [
      "POST"
    ],
    "paramNames": [],
    "path": "/admin/home_nav",
    "regexp": "/^\\/admin\\/home_nav(?:\\/(?=$))?$/",
    "stack": [
      "middleware",
      "wrappedController"
    ]
  },
  {
    "name": null,
    "methods": [
      "PATCH",
      "PUT"
    ],
    "paramNames": [
      {
        "name": "id",
        "prefix": "/",
        "delimiter": "/",
        "optional": false,
        "repeat": false,
        "partial": false,
        "asterisk": false,
        "pattern": "[^\\/]+?"
      }
    ],
    "path": "/admin/home_nav/:id",
    "regexp": "/^\\/admin\\/home_nav\\/((?:[^\\/]+?))(?:\\/(?=$))?$/",
    "stack": [
      "middleware",
      "wrappedController"
    ]
  },
  {
    "name": "destroy_",
    "methods": [
      "DELETE"
    ],
    "paramNames": [
      {
        "name": "id",
        "prefix": "/",
        "delimiter": "/",
        "optional": false,
        "repeat": false,
        "partial": false,
        "asterisk": false,
        "pattern": "[^\\/]+?"
      }
    ],
    "path": "/admin/home_nav/:id",
    "regexp": "/^\\/admin\\/home_nav\\/((?:[^\\/]+?))(?:\\/(?=$))?$/",
    "stack": [
      "middleware",
      "wrappedController"
    ]
  },
  {
    "name": null,
    "methods": [
      "DELETE"
    ],
    "paramNames": [],
    "path": "/admin/home_nav",
    "regexp": "/^\\/admin\\/home_nav(?:\\/(?=$))?$/",
    "stack": [
      "middleware",
      "wrappedController"
    ]
  },
  {
    "name": null,
    "methods": [
      "POST"
    ],
    "paramNames": [],
    "path": "/admin/home_nav/sort",
    "regexp": "/^\\/admin\\/home_nav\\/sort(?:\\/(?=$))?$/",
    "stack": [
      "middleware",
      "wrappedController"
    ]
  },
  {
    "name": null,
    "methods": [
      "HEAD",
      "GET"
    ],
    "paramNames": [],
    "path": "/admin/home_nav/data",
    "regexp": "/^\\/admin\\/home_nav\\/data(?:\\/(?=$))?$/",
    "stack": [
      "middleware",
      "wrappedController"
    ]
  },
  {
    "name": null,
    "methods": [
      "POST"
    ],
    "paramNames": [],
    "path": "/admin/login",
    "regexp": "/^\\/admin\\/login(?:\\/(?=$))?$/",
    "stack": [
      "wrappedController"
    ]
  },
  {
    "name": null,
    "methods": [
      "HEAD",
      "GET"
    ],
    "paramNames": [],
    "path": "/admin/info",
    "regexp": "/^\\/admin\\/info(?:\\/(?=$))?$/",
    "stack": [
      "middleware",
      "wrappedController"
    ]
  },
  {
    "name": null,
    "methods": [
      "POST"
    ],
    "paramNames": [],
    "path": "/admin/upload",
    "regexp": "/^\\/admin\\/upload(?:\\/(?=$))?$/",
    "stack": [
      "middleware",
      "wrappedController"
    ]
  },
  {
    "name": null,
    "methods": [
      "DELETE"
    ],
    "paramNames": [],
    "path": "/admin/upload",
    "regexp": "/^\\/admin\\/upload(?:\\/(?=$))?$/",
    "stack": [
      "middleware",
      "wrappedController"
    ]
  },
  {
    "name": "s",
    "methods": [
      "HEAD",
      "GET"
    ],
    "paramNames": [],
    "path": "/admin/user",
    "regexp": "/^\\/admin\\/user(?:\\/(?=$))?$/",
    "stack": [
      "middleware",
      "wrappedController"
    ]
  },
  {
    "name": "s",
    "methods": [
      "POST"
    ],
    "paramNames": [],
    "path": "/admin/user",
    "regexp": "/^\\/admin\\/user(?:\\/(?=$))?$/",
    "stack": [
      "middleware",
      "wrappedController"
    ]
  },
  {
    "name": null,
    "methods": [
      "HEAD",
      "GET"
    ],
    "paramNames": [
      {
        "name": "id",
        "prefix": "/",
        "delimiter": "/",
        "optional": false,
        "repeat": false,
        "partial": false,
        "asterisk": false,
        "pattern": "[^\\/]+?"
      }
    ],
    "path": "/admin/user/:id",
    "regexp": "/^\\/admin\\/user\\/((?:[^\\/]+?))(?:\\/(?=$))?$/",
    "stack": [
      "middleware",
      "wrappedController"
    ]
  },
  {
    "name": null,
    "methods": [
      "PATCH",
      "PUT"
    ],
    "paramNames": [
      {
        "name": "id",
        "prefix": "/",
        "delimiter": "/",
        "optional": false,
        "repeat": false,
        "partial": false,
        "asterisk": false,
        "pattern": "[^\\/]+?"
      }
    ],
    "path": "/admin/user/:id",
    "regexp": "/^\\/admin\\/user\\/((?:[^\\/]+?))(?:\\/(?=$))?$/",
    "stack": [
      "middleware",
      "wrappedController"
    ]
  },
  {
    "name": "destroy_",
    "methods": [
      "DELETE"
    ],
    "paramNames": [
      {
        "name": "id",
        "prefix": "/",
        "delimiter": "/",
        "optional": false,
        "repeat": false,
        "partial": false,
        "asterisk": false,
        "pattern": "[^\\/]+?"
      }
    ],
    "path": "/admin/user/:id",
    "regexp": "/^\\/admin\\/user\\/((?:[^\\/]+?))(?:\\/(?=$))?$/",
    "stack": [
      "middleware",
      "wrappedController"
    ]
  },
  {
    "name": null,
    "methods": [
      "DELETE"
    ],
    "paramNames": [],
    "path": "/admin/user",
    "regexp": "/^\\/admin\\/user(?:\\/(?=$))?$/",
    "stack": [
      "middleware",
      "wrappedController"
    ]
  },
  {
    "name": "s",
    "methods": [
      "HEAD",
      "GET"
    ],
    "paramNames": [],
    "path": "/admin/menu",
    "regexp": "/^\\/admin\\/menu(?:\\/(?=$))?$/",
    "stack": [
      "middleware",
      "wrappedController"
    ]
  },
  {
    "name": "s",
    "methods": [
      "POST"
    ],
    "paramNames": [],
    "path": "/admin/menu",
    "regexp": "/^\\/admin\\/menu(?:\\/(?=$))?$/",
    "stack": [
      "middleware",
      "wrappedController"
    ]
  },
  {
    "name": null,
    "methods": [
      "PATCH",
      "PUT"
    ],
    "paramNames": [
      {
        "name": "id",
        "prefix": "/",
        "delimiter": "/",
        "optional": false,
        "repeat": false,
        "partial": false,
        "asterisk": false,
        "pattern": "[^\\/]+?"
      }
    ],
    "path": "/admin/menu/:id",
    "regexp": "/^\\/admin\\/menu\\/((?:[^\\/]+?))(?:\\/(?=$))?$/",
    "stack": [
      "middleware",
      "wrappedController"
    ]
  },
  {
    "name": "destroy_",
    "methods": [
      "DELETE"
    ],
    "paramNames": [
      {
        "name": "id",
        "prefix": "/",
        "delimiter": "/",
        "optional": false,
        "repeat": false,
        "partial": false,
        "asterisk": false,
        "pattern": "[^\\/]+?"
      }
    ],
    "path": "/admin/menu/:id",
    "regexp": "/^\\/admin\\/menu\\/((?:[^\\/]+?))(?:\\/(?=$))?$/",
    "stack": [
      "middleware",
      "wrappedController"
    ]
  },
  {
    "name": null,
    "methods": [
      "POST"
    ],
    "paramNames": [],
    "path": "/admin/menu/sort",
    "regexp": "/^\\/admin\\/menu\\/sort(?:\\/(?=$))?$/",
    "stack": [
      "middleware",
      "wrappedController"
    ]
  },
  {
    "name": "s",
    "methods": [
      "HEAD",
      "GET"
    ],
    "paramNames": [],
    "path": "/admin/role",
    "regexp": "/^\\/admin\\/role(?:\\/(?=$))?$/",
    "stack": [
      "middleware",
      "wrappedController"
    ]
  },
  {
    "name": "s",
    "methods": [
      "POST"
    ],
    "paramNames": [],
    "path": "/admin/role",
    "regexp": "/^\\/admin\\/role(?:\\/(?=$))?$/",
    "stack": [
      "middleware",
      "wrappedController"
    ]
  },
  {
    "name": null,
    "methods": [
      "PATCH",
      "PUT"
    ],
    "paramNames": [
      {
        "name": "id",
        "prefix": "/",
        "delimiter": "/",
        "optional": false,
        "repeat": false,
        "partial": false,
        "asterisk": false,
        "pattern": "[^\\/]+?"
      }
    ],
    "path": "/admin/role/:id",
    "regexp": "/^\\/admin\\/role\\/((?:[^\\/]+?))(?:\\/(?=$))?$/",
    "stack": [
      "middleware",
      "wrappedController"
    ]
  },
  {
    "name": "destroy_",
    "methods": [
      "DELETE"
    ],
    "paramNames": [
      {
        "name": "id",
        "prefix": "/",
        "delimiter": "/",
        "optional": false,
        "repeat": false,
        "partial": false,
        "asterisk": false,
        "pattern": "[^\\/]+?"
      }
    ],
    "path": "/admin/role/:id",
    "regexp": "/^\\/admin\\/role\\/((?:[^\\/]+?))(?:\\/(?=$))?$/",
    "stack": [
      "middleware",
      "wrappedController"
    ]
  },
  {
    "name": null,
    "methods": [
      "DELETE"
    ],
    "paramNames": [],
    "path": "/admin/role",
    "regexp": "/^\\/admin\\/role(?:\\/(?=$))?$/",
    "stack": [
      "middleware",
      "wrappedController"
    ]
  },
  {
    "name": "s",
    "methods": [
      "HEAD",
      "GET"
    ],
    "paramNames": [],
    "path": "/admin/wxUser",
    "regexp": "/^\\/admin\\/wxUser(?:\\/(?=$))?$/",
    "stack": [
      "middleware",
      "wrappedController"
    ]
  },
  {
    "name": "destroy_",
    "methods": [
      "DELETE"
    ],
    "paramNames": [
      {
        "name": "id",
        "prefix": "/",
        "delimiter": "/",
        "optional": false,
        "repeat": false,
        "partial": false,
        "asterisk": false,
        "pattern": "[^\\/]+?"
      }
    ],
    "path": "/admin/wxUser/:id",
    "regexp": "/^\\/admin\\/wxUser\\/((?:[^\\/]+?))(?:\\/(?=$))?$/",
    "stack": [
      "middleware",
      "wrappedController"
    ]
  },
  {
    "name": null,
    "methods": [
      "DELETE"
    ],
    "paramNames": [],
    "path": "/admin/wxUser",
    "regexp": "/^\\/admin\\/wxUser(?:\\/(?=$))?$/",
    "stack": [
      "middleware",
      "wrappedController"
    ]
  },
  {
    "name": "s",
    "methods": [
      "HEAD",
      "GET"
    ],
    "paramNames": [],
    "path": "/admin/category",
    "regexp": "/^\\/admin\\/category(?:\\/(?=$))?$/",
    "stack": [
      "middleware",
      "wrappedController"
    ]
  },
  {
    "name": "s",
    "methods": [
      "POST"
    ],
    "paramNames": [],
    "path": "/admin/category",
    "regexp": "/^\\/admin\\/category(?:\\/(?=$))?$/",
    "stack": [
      "middleware",
      "wrappedController"
    ]
  },
  {
    "name": null,
    "methods": [
      "PATCH",
      "PUT"
    ],
    "paramNames": [
      {
        "name": "id",
        "prefix": "/",
        "delimiter": "/",
        "optional": false,
        "repeat": false,
        "partial": false,
        "asterisk": false,
        "pattern": "[^\\/]+?"
      }
    ],
    "path": "/admin/category/:id",
    "regexp": "/^\\/admin\\/category\\/((?:[^\\/]+?))(?:\\/(?=$))?$/",
    "stack": [
      "middleware",
      "wrappedController"
    ]
  },
  {
    "name": "destroy_",
    "methods": [
      "DELETE"
    ],
    "paramNames": [
      {
        "name": "id",
        "prefix": "/",
        "delimiter": "/",
        "optional": false,
        "repeat": false,
        "partial": false,
        "asterisk": false,
        "pattern": "[^\\/]+?"
      }
    ],
    "path": "/admin/category/:id",
    "regexp": "/^\\/admin\\/category\\/((?:[^\\/]+?))(?:\\/(?=$))?$/",
    "stack": [
      "middleware",
      "wrappedController"
    ]
  },
  {
    "name": null,
    "methods": [
      "DELETE"
    ],
    "paramNames": [],
    "path": "/admin/category",
    "regexp": "/^\\/admin\\/category(?:\\/(?=$))?$/",
    "stack": [
      "middleware",
      "wrappedController"
    ]
  },
  {
    "name": null,
    "methods": [
      "POST"
    ],
    "paramNames": [],
    "path": "/admin/category/sort",
    "regexp": "/^\\/admin\\/category\\/sort(?:\\/(?=$))?$/",
    "stack": [
      "middleware",
      "wrappedController"
    ]
  },
  {
    "name": "s",
    "methods": [
      "HEAD",
      "GET"
    ],
    "paramNames": [],
    "path": "/admin/goods",
    "regexp": "/^\\/admin\\/goods(?:\\/(?=$))?$/",
    "stack": [
      "middleware",
      "wrappedController"
    ]
  },
  {
    "name": "s",
    "methods": [
      "POST"
    ],
    "paramNames": [],
    "path": "/admin/goods",
    "regexp": "/^\\/admin\\/goods(?:\\/(?=$))?$/",
    "stack": [
      "middleware",
      "wrappedController"
    ]
  },
  {
    "name": null,
    "methods": [
      "HEAD",
      "GET"
    ],
    "paramNames": [
      {
        "name": "id",
        "prefix": "/",
        "delimiter": "/",
        "optional": false,
        "repeat": false,
        "partial": false,
        "asterisk": false,
        "pattern": "[^\\/]+?"
      }
    ],
    "path": "/admin/goods/:id",
    "regexp": "/^\\/admin\\/goods\\/((?:[^\\/]+?))(?:\\/(?=$))?$/",
    "stack": [
      "middleware",
      "wrappedController"
    ]
  },
  {
    "name": null,
    "methods": [
      "PATCH",
      "PUT"
    ],
    "paramNames": [
      {
        "name": "id",
        "prefix": "/",
        "delimiter": "/",
        "optional": false,
        "repeat": false,
        "partial": false,
        "asterisk": false,
        "pattern": "[^\\/]+?"
      }
    ],
    "path": "/admin/goods/:id",
    "regexp": "/^\\/admin\\/goods\\/((?:[^\\/]+?))(?:\\/(?=$))?$/",
    "stack": [
      "middleware",
      "wrappedController"
    ]
  },
  {
    "name": "destroy_",
    "methods": [
      "DELETE"
    ],
    "paramNames": [
      {
        "name": "id",
        "prefix": "/",
        "delimiter": "/",
        "optional": false,
        "repeat": false,
        "partial": false,
        "asterisk": false,
        "pattern": "[^\\/]+?"
      }
    ],
    "path": "/admin/goods/:id",
    "regexp": "/^\\/admin\\/goods\\/((?:[^\\/]+?))(?:\\/(?=$))?$/",
    "stack": [
      "middleware",
      "wrappedController"
    ]
  },
  {
    "name": null,
    "methods": [
      "DELETE"
    ],
    "paramNames": [],
    "path": "/admin/goods",
    "regexp": "/^\\/admin\\/goods(?:\\/(?=$))?$/",
    "stack": [
      "middleware",
      "wrappedController"
    ]
  },
  {
    "name": "s",
    "methods": [
      "HEAD",
      "GET"
    ],
    "paramNames": [],
    "path": "/admin/banner",
    "regexp": "/^\\/admin\\/banner(?:\\/(?=$))?$/",
    "stack": [
      "middleware",
      "wrappedController"
    ]
  },
  {
    "name": "s",
    "methods": [
      "POST"
    ],
    "paramNames": [],
    "path": "/admin/banner",
    "regexp": "/^\\/admin\\/banner(?:\\/(?=$))?$/",
    "stack": [
      "middleware",
      "wrappedController"
    ]
  },
  {
    "name": null,
    "methods": [
      "PATCH",
      "PUT"
    ],
    "paramNames": [
      {
        "name": "id",
        "prefix": "/",
        "delimiter": "/",
        "optional": false,
        "repeat": false,
        "partial": false,
        "asterisk": false,
        "pattern": "[^\\/]+?"
      }
    ],
    "path": "/admin/banner/:id",
    "regexp": "/^\\/admin\\/banner\\/((?:[^\\/]+?))(?:\\/(?=$))?$/",
    "stack": [
      "middleware",
      "wrappedController"
    ]
  },
  {
    "name": "destroy_",
    "methods": [
      "DELETE"
    ],
    "paramNames": [
      {
        "name": "id",
        "prefix": "/",
        "delimiter": "/",
        "optional": false,
        "repeat": false,
        "partial": false,
        "asterisk": false,
        "pattern": "[^\\/]+?"
      }
    ],
    "path": "/admin/banner/:id",
    "regexp": "/^\\/admin\\/banner\\/((?:[^\\/]+?))(?:\\/(?=$))?$/",
    "stack": [
      "middleware",
      "wrappedController"
    ]
  },
  {
    "name": null,
    "methods": [
      "DELETE"
    ],
    "paramNames": [],
    "path": "/admin/banner",
    "regexp": "/^\\/admin\\/banner(?:\\/(?=$))?$/",
    "stack": [
      "middleware",
      "wrappedController"
    ]
  },
  {
    "name": null,
    "methods": [
      "POST"
    ],
    "paramNames": [],
    "path": "/admin/banner/sort",
    "regexp": "/^\\/admin\\/banner\\/sort(?:\\/(?=$))?$/",
    "stack": [
      "middleware",
      "wrappedController"
    ]
  },
  {
    "name": "s",
    "methods": [
      "HEAD",
      "GET"
    ],
    "paramNames": [],
    "path": "/admin/home_nav",
    "regexp": "/^\\/admin\\/home_nav(?:\\/(?=$))?$/",
    "stack": [
      "middleware",
      "wrappedController"
    ]
  },
  {
    "name": "s",
    "methods": [
      "POST"
    ],
    "paramNames": [],
    "path": "/admin/home_nav",
    "regexp": "/^\\/admin\\/home_nav(?:\\/(?=$))?$/",
    "stack": [
      "middleware",
      "wrappedController"
    ]
  },
  {
    "name": null,
    "methods": [
      "PATCH",
      "PUT"
    ],
    "paramNames": [
      {
        "name": "id",
        "prefix": "/",
        "delimiter": "/",
        "optional": false,
        "repeat": false,
        "partial": false,
        "asterisk": false,
        "pattern": "[^\\/]+?"
      }
    ],
    "path": "/admin/home_nav/:id",
    "regexp": "/^\\/admin\\/home_nav\\/((?:[^\\/]+?))(?:\\/(?=$))?$/",
    "stack": [
      "middleware",
      "wrappedController"
    ]
  },
  {
    "name": "destroy_",
    "methods": [
      "DELETE"
    ],
    "paramNames": [
      {
        "name": "id",
        "prefix": "/",
        "delimiter": "/",
        "optional": false,
        "repeat": false,
        "partial": false,
        "asterisk": false,
        "pattern": "[^\\/]+?"
      }
    ],
    "path": "/admin/home_nav/:id",
    "regexp": "/^\\/admin\\/home_nav\\/((?:[^\\/]+?))(?:\\/(?=$))?$/",
    "stack": [
      "middleware",
      "wrappedController"
    ]
  },
  {
    "name": null,
    "methods": [
      "DELETE"
    ],
    "paramNames": [],
    "path": "/admin/home_nav",
    "regexp": "/^\\/admin\\/home_nav(?:\\/(?=$))?$/",
    "stack": [
      "middleware",
      "wrappedController"
    ]
  },
  {
    "name": null,
    "methods": [
      "POST"
    ],
    "paramNames": [],
    "path": "/admin/home_nav/sort",
    "regexp": "/^\\/admin\\/home_nav\\/sort(?:\\/(?=$))?$/",
    "stack": [
      "middleware",
      "wrappedController"
    ]
  },
  {
    "name": null,
    "methods": [
      "HEAD",
      "GET"
    ],
    "paramNames": [],
    "path": "/admin/home_nav/data",
    "regexp": "/^\\/admin\\/home_nav\\/data(?:\\/(?=$))?$/",
    "stack": [
      "middleware",
      "wrappedController"
    ]
  },
  {
    "name": null,
    "methods": [
      "HEAD",
      "GET"
    ],
    "paramNames": [],
    "path": "/weapp/login",
    "regexp": "/^\\/weapp\\/login(?:\\/(?=$))?$/",
    "stack": [
      "wrappedController"
    ]
  },
  {
    "name": null,
    "methods": [
      "POST"
    ],
    "paramNames": [],
    "path": "/weapp/user/update",
    "regexp": "/^\\/weapp\\/user\\/update(?:\\/(?=$))?$/",
    "stack": [
      "middleware",
      "wrappedController"
    ]
  },
  {
    "name": null,
    "methods": [
      "HEAD",
      "GET"
    ],
    "paramNames": [],
    "path": "/weapp/banner",
    "regexp": "/^\\/weapp\\/banner(?:\\/(?=$))?$/",
    "stack": [
      "wrappedController"
    ]
  },
  {
    "name": null,
    "methods": [
      "HEAD",
      "GET"
    ],
    "paramNames": [],
    "path": "/weapp/home_nav",
    "regexp": "/^\\/weapp\\/home_nav(?:\\/(?=$))?$/",
    "stack": [
      "wrappedController"
    ]
  },
  {
    "name": null,
    "methods": [
      "HEAD",
      "GET"
    ],
    "paramNames": [],
    "path": "/weapp/recommend",
    "regexp": "/^\\/weapp\\/recommend(?:\\/(?=$))?$/",
    "stack": [
      "wrappedController"
    ]
  },
  {
    "name": null,
    "methods": [
      "HEAD",
      "GET"
    ],
    "paramNames": [],
    "path": "/weapp/category",
    "regexp": "/^\\/weapp\\/category(?:\\/(?=$))?$/",
    "stack": [
      "wrappedController"
    ]
  },
  {
    "name": null,
    "methods": [
      "HEAD",
      "GET"
    ],
    "paramNames": [],
    "path": "/weapp/login",
    "regexp": "/^\\/weapp\\/login(?:\\/(?=$))?$/",
    "stack": [
      "wrappedController"
    ]
  },
  {
    "name": null,
    "methods": [
      "POST"
    ],
    "paramNames": [],
    "path": "/weapp/user/update",
    "regexp": "/^\\/weapp\\/user\\/update(?:\\/(?=$))?$/",
    "stack": [
      "middleware",
      "wrappedController"
    ]
  },
  {
    "name": null,
    "methods": [
      "HEAD",
      "GET"
    ],
    "paramNames": [],
    "path": "/weapp/banner",
    "regexp": "/^\\/weapp\\/banner(?:\\/(?=$))?$/",
    "stack": [
      "wrappedController"
    ]
  },
  {
    "name": null,
    "methods": [
      "HEAD",
      "GET"
    ],
    "paramNames": [],
    "path": "/weapp/home_nav",
    "regexp": "/^\\/weapp\\/home_nav(?:\\/(?=$))?$/",
    "stack": [
      "wrappedController"
    ]
  },
  {
    "name": null,
    "methods": [
      "HEAD",
      "GET"
    ],
    "paramNames": [],
    "path": "/weapp/recommend",
    "regexp": "/^\\/weapp\\/recommend(?:\\/(?=$))?$/",
    "stack": [
      "wrappedController"
    ]
  },
  {
    "name": null,
    "methods": [
      "HEAD",
      "GET"
    ],
    "paramNames": [],
    "path": "/weapp/category",
    "regexp": "/^\\/weapp\\/category(?:\\/(?=$))?$/",
    "stack": [
      "wrappedController"
    ]
  },
  {
    "name": null,
    "methods": [
      "POST"
    ],
    "paramNames": [],
    "path": "/admin/login",
    "regexp": "/^\\/admin\\/login(?:\\/(?=$))?$/",
    "stack": [
      "wrappedController"
    ]
  },
  {
    "name": null,
    "methods": [
      "HEAD",
      "GET"
    ],
    "paramNames": [],
    "path": "/admin/info",
    "regexp": "/^\\/admin\\/info(?:\\/(?=$))?$/",
    "stack": [
      "middleware",
      "wrappedController"
    ]
  },
  {
    "name": null,
    "methods": [
      "POST"
    ],
    "paramNames": [],
    "path": "/admin/upload",
    "regexp": "/^\\/admin\\/upload(?:\\/(?=$))?$/",
    "stack": [
      "middleware",
      "wrappedController"
    ]
  },
  {
    "name": null,
    "methods": [
      "DELETE"
    ],
    "paramNames": [],
    "path": "/admin/upload",
    "regexp": "/^\\/admin\\/upload(?:\\/(?=$))?$/",
    "stack": [
      "middleware",
      "wrappedController"
    ]
  },
  {
    "name": "s",
    "methods": [
      "HEAD",
      "GET"
    ],
    "paramNames": [],
    "path": "/admin/user",
    "regexp": "/^\\/admin\\/user(?:\\/(?=$))?$/",
    "stack": [
      "middleware",
      "wrappedController"
    ]
  },
  {
    "name": "s",
    "methods": [
      "POST"
    ],
    "paramNames": [],
    "path": "/admin/user",
    "regexp": "/^\\/admin\\/user(?:\\/(?=$))?$/",
    "stack": [
      "middleware",
      "wrappedController"
    ]
  },
  {
    "name": null,
    "methods": [
      "HEAD",
      "GET"
    ],
    "paramNames": [
      {
        "name": "id",
        "prefix": "/",
        "delimiter": "/",
        "optional": false,
        "repeat": false,
        "partial": false,
        "asterisk": false,
        "pattern": "[^\\/]+?"
      }
    ],
    "path": "/admin/user/:id",
    "regexp": "/^\\/admin\\/user\\/((?:[^\\/]+?))(?:\\/(?=$))?$/",
    "stack": [
      "middleware",
      "wrappedController"
    ]
  },
  {
    "name": null,
    "methods": [
      "PATCH",
      "PUT"
    ],
    "paramNames": [
      {
        "name": "id",
        "prefix": "/",
        "delimiter": "/",
        "optional": false,
        "repeat": false,
        "partial": false,
        "asterisk": false,
        "pattern": "[^\\/]+?"
      }
    ],
    "path": "/admin/user/:id",
    "regexp": "/^\\/admin\\/user\\/((?:[^\\/]+?))(?:\\/(?=$))?$/",
    "stack": [
      "middleware",
      "wrappedController"
    ]
  },
  {
    "name": "destroy_",
    "methods": [
      "DELETE"
    ],
    "paramNames": [
      {
        "name": "id",
        "prefix": "/",
        "delimiter": "/",
        "optional": false,
        "repeat": false,
        "partial": false,
        "asterisk": false,
        "pattern": "[^\\/]+?"
      }
    ],
    "path": "/admin/user/:id",
    "regexp": "/^\\/admin\\/user\\/((?:[^\\/]+?))(?:\\/(?=$))?$/",
    "stack": [
      "middleware",
      "wrappedController"
    ]
  },
  {
    "name": null,
    "methods": [
      "DELETE"
    ],
    "paramNames": [],
    "path": "/admin/user",
    "regexp": "/^\\/admin\\/user(?:\\/(?=$))?$/",
    "stack": [
      "middleware",
      "wrappedController"
    ]
  },
  {
    "name": "s",
    "methods": [
      "HEAD",
      "GET"
    ],
    "paramNames": [],
    "path": "/admin/menu",
    "regexp": "/^\\/admin\\/menu(?:\\/(?=$))?$/",
    "stack": [
      "middleware",
      "wrappedController"
    ]
  },
  {
    "name": "s",
    "methods": [
      "POST"
    ],
    "paramNames": [],
    "path": "/admin/menu",
    "regexp": "/^\\/admin\\/menu(?:\\/(?=$))?$/",
    "stack": [
      "middleware",
      "wrappedController"
    ]
  },
  {
    "name": null,
    "methods": [
      "PATCH",
      "PUT"
    ],
    "paramNames": [
      {
        "name": "id",
        "prefix": "/",
        "delimiter": "/",
        "optional": false,
        "repeat": false,
        "partial": false,
        "asterisk": false,
        "pattern": "[^\\/]+?"
      }
    ],
    "path": "/admin/menu/:id",
    "regexp": "/^\\/admin\\/menu\\/((?:[^\\/]+?))(?:\\/(?=$))?$/",
    "stack": [
      "middleware",
      "wrappedController"
    ]
  },
  {
    "name": "destroy_",
    "methods": [
      "DELETE"
    ],
    "paramNames": [
      {
        "name": "id",
        "prefix": "/",
        "delimiter": "/",
        "optional": false,
        "repeat": false,
        "partial": false,
        "asterisk": false,
        "pattern": "[^\\/]+?"
      }
    ],
    "path": "/admin/menu/:id",
    "regexp": "/^\\/admin\\/menu\\/((?:[^\\/]+?))(?:\\/(?=$))?$/",
    "stack": [
      "middleware",
      "wrappedController"
    ]
  },
  {
    "name": null,
    "methods": [
      "POST"
    ],
    "paramNames": [],
    "path": "/admin/menu/sort",
    "regexp": "/^\\/admin\\/menu\\/sort(?:\\/(?=$))?$/",
    "stack": [
      "middleware",
      "wrappedController"
    ]
  },
  {
    "name": "s",
    "methods": [
      "HEAD",
      "GET"
    ],
    "paramNames": [],
    "path": "/admin/role",
    "regexp": "/^\\/admin\\/role(?:\\/(?=$))?$/",
    "stack": [
      "middleware",
      "wrappedController"
    ]
  },
  {
    "name": "s",
    "methods": [
      "POST"
    ],
    "paramNames": [],
    "path": "/admin/role",
    "regexp": "/^\\/admin\\/role(?:\\/(?=$))?$/",
    "stack": [
      "middleware",
      "wrappedController"
    ]
  },
  {
    "name": null,
    "methods": [
      "PATCH",
      "PUT"
    ],
    "paramNames": [
      {
        "name": "id",
        "prefix": "/",
        "delimiter": "/",
        "optional": false,
        "repeat": false,
        "partial": false,
        "asterisk": false,
        "pattern": "[^\\/]+?"
      }
    ],
    "path": "/admin/role/:id",
    "regexp": "/^\\/admin\\/role\\/((?:[^\\/]+?))(?:\\/(?=$))?$/",
    "stack": [
      "middleware",
      "wrappedController"
    ]
  },
  {
    "name": "destroy_",
    "methods": [
      "DELETE"
    ],
    "paramNames": [
      {
        "name": "id",
        "prefix": "/",
        "delimiter": "/",
        "optional": false,
        "repeat": false,
        "partial": false,
        "asterisk": false,
        "pattern": "[^\\/]+?"
      }
    ],
    "path": "/admin/role/:id",
    "regexp": "/^\\/admin\\/role\\/((?:[^\\/]+?))(?:\\/(?=$))?$/",
    "stack": [
      "middleware",
      "wrappedController"
    ]
  },
  {
    "name": null,
    "methods": [
      "DELETE"
    ],
    "paramNames": [],
    "path": "/admin/role",
    "regexp": "/^\\/admin\\/role(?:\\/(?=$))?$/",
    "stack": [
      "middleware",
      "wrappedController"
    ]
  },
  {
    "name": "s",
    "methods": [
      "HEAD",
      "GET"
    ],
    "paramNames": [],
    "path": "/admin/wxUser",
    "regexp": "/^\\/admin\\/wxUser(?:\\/(?=$))?$/",
    "stack": [
      "middleware",
      "wrappedController"
    ]
  },
  {
    "name": "destroy_",
    "methods": [
      "DELETE"
    ],
    "paramNames": [
      {
        "name": "id",
        "prefix": "/",
        "delimiter": "/",
        "optional": false,
        "repeat": false,
        "partial": false,
        "asterisk": false,
        "pattern": "[^\\/]+?"
      }
    ],
    "path": "/admin/wxUser/:id",
    "regexp": "/^\\/admin\\/wxUser\\/((?:[^\\/]+?))(?:\\/(?=$))?$/",
    "stack": [
      "middleware",
      "wrappedController"
    ]
  },
  {
    "name": null,
    "methods": [
      "DELETE"
    ],
    "paramNames": [],
    "path": "/admin/wxUser",
    "regexp": "/^\\/admin\\/wxUser(?:\\/(?=$))?$/",
    "stack": [
      "middleware",
      "wrappedController"
    ]
  },
  {
    "name": "s",
    "methods": [
      "HEAD",
      "GET"
    ],
    "paramNames": [],
    "path": "/admin/category",
    "regexp": "/^\\/admin\\/category(?:\\/(?=$))?$/",
    "stack": [
      "middleware",
      "wrappedController"
    ]
  },
  {
    "name": "s",
    "methods": [
      "POST"
    ],
    "paramNames": [],
    "path": "/admin/category",
    "regexp": "/^\\/admin\\/category(?:\\/(?=$))?$/",
    "stack": [
      "middleware",
      "wrappedController"
    ]
  },
  {
    "name": null,
    "methods": [
      "PATCH",
      "PUT"
    ],
    "paramNames": [
      {
        "name": "id",
        "prefix": "/",
        "delimiter": "/",
        "optional": false,
        "repeat": false,
        "partial": false,
        "asterisk": false,
        "pattern": "[^\\/]+?"
      }
    ],
    "path": "/admin/category/:id",
    "regexp": "/^\\/admin\\/category\\/((?:[^\\/]+?))(?:\\/(?=$))?$/",
    "stack": [
      "middleware",
      "wrappedController"
    ]
  },
  {
    "name": "destroy_",
    "methods": [
      "DELETE"
    ],
    "paramNames": [
      {
        "name": "id",
        "prefix": "/",
        "delimiter": "/",
        "optional": false,
        "repeat": false,
        "partial": false,
        "asterisk": false,
        "pattern": "[^\\/]+?"
      }
    ],
    "path": "/admin/category/:id",
    "regexp": "/^\\/admin\\/category\\/((?:[^\\/]+?))(?:\\/(?=$))?$/",
    "stack": [
      "middleware",
      "wrappedController"
    ]
  },
  {
    "name": null,
    "methods": [
      "DELETE"
    ],
    "paramNames": [],
    "path": "/admin/category",
    "regexp": "/^\\/admin\\/category(?:\\/(?=$))?$/",
    "stack": [
      "middleware",
      "wrappedController"
    ]
  },
  {
    "name": null,
    "methods": [
      "POST"
    ],
    "paramNames": [],
    "path": "/admin/category/sort",
    "regexp": "/^\\/admin\\/category\\/sort(?:\\/(?=$))?$/",
    "stack": [
      "middleware",
      "wrappedController"
    ]
  },
  {
    "name": "s",
    "methods": [
      "HEAD",
      "GET"
    ],
    "paramNames": [],
    "path": "/admin/goods",
    "regexp": "/^\\/admin\\/goods(?:\\/(?=$))?$/",
    "stack": [
      "middleware",
      "wrappedController"
    ]
  },
  {
    "name": "s",
    "methods": [
      "POST"
    ],
    "paramNames": [],
    "path": "/admin/goods",
    "regexp": "/^\\/admin\\/goods(?:\\/(?=$))?$/",
    "stack": [
      "middleware",
      "wrappedController"
    ]
  },
  {
    "name": null,
    "methods": [
      "HEAD",
      "GET"
    ],
    "paramNames": [
      {
        "name": "id",
        "prefix": "/",
        "delimiter": "/",
        "optional": false,
        "repeat": false,
        "partial": false,
        "asterisk": false,
        "pattern": "[^\\/]+?"
      }
    ],
    "path": "/admin/goods/:id",
    "regexp": "/^\\/admin\\/goods\\/((?:[^\\/]+?))(?:\\/(?=$))?$/",
    "stack": [
      "middleware",
      "wrappedController"
    ]
  },
  {
    "name": null,
    "methods": [
      "PATCH",
      "PUT"
    ],
    "paramNames": [
      {
        "name": "id",
        "prefix": "/",
        "delimiter": "/",
        "optional": false,
        "repeat": false,
        "partial": false,
        "asterisk": false,
        "pattern": "[^\\/]+?"
      }
    ],
    "path": "/admin/goods/:id",
    "regexp": "/^\\/admin\\/goods\\/((?:[^\\/]+?))(?:\\/(?=$))?$/",
    "stack": [
      "middleware",
      "wrappedController"
    ]
  },
  {
    "name": "destroy_",
    "methods": [
      "DELETE"
    ],
    "paramNames": [
      {
        "name": "id",
        "prefix": "/",
        "delimiter": "/",
        "optional": false,
        "repeat": false,
        "partial": false,
        "asterisk": false,
        "pattern": "[^\\/]+?"
      }
    ],
    "path": "/admin/goods/:id",
    "regexp": "/^\\/admin\\/goods\\/((?:[^\\/]+?))(?:\\/(?=$))?$/",
    "stack": [
      "middleware",
      "wrappedController"
    ]
  },
  {
    "name": null,
    "methods": [
      "DELETE"
    ],
    "paramNames": [],
    "path": "/admin/goods",
    "regexp": "/^\\/admin\\/goods(?:\\/(?=$))?$/",
    "stack": [
      "middleware",
      "wrappedController"
    ]
  },
  {
    "name": "s",
    "methods": [
      "HEAD",
      "GET"
    ],
    "paramNames": [],
    "path": "/admin/banner",
    "regexp": "/^\\/admin\\/banner(?:\\/(?=$))?$/",
    "stack": [
      "middleware",
      "wrappedController"
    ]
  },
  {
    "name": "s",
    "methods": [
      "POST"
    ],
    "paramNames": [],
    "path": "/admin/banner",
    "regexp": "/^\\/admin\\/banner(?:\\/(?=$))?$/",
    "stack": [
      "middleware",
      "wrappedController"
    ]
  },
  {
    "name": null,
    "methods": [
      "PATCH",
      "PUT"
    ],
    "paramNames": [
      {
        "name": "id",
        "prefix": "/",
        "delimiter": "/",
        "optional": false,
        "repeat": false,
        "partial": false,
        "asterisk": false,
        "pattern": "[^\\/]+?"
      }
    ],
    "path": "/admin/banner/:id",
    "regexp": "/^\\/admin\\/banner\\/((?:[^\\/]+?))(?:\\/(?=$))?$/",
    "stack": [
      "middleware",
      "wrappedController"
    ]
  },
  {
    "name": "destroy_",
    "methods": [
      "DELETE"
    ],
    "paramNames": [
      {
        "name": "id",
        "prefix": "/",
        "delimiter": "/",
        "optional": false,
        "repeat": false,
        "partial": false,
        "asterisk": false,
        "pattern": "[^\\/]+?"
      }
    ],
    "path": "/admin/banner/:id",
    "regexp": "/^\\/admin\\/banner\\/((?:[^\\/]+?))(?:\\/(?=$))?$/",
    "stack": [
      "middleware",
      "wrappedController"
    ]
  },
  {
    "name": null,
    "methods": [
      "DELETE"
    ],
    "paramNames": [],
    "path": "/admin/banner",
    "regexp": "/^\\/admin\\/banner(?:\\/(?=$))?$/",
    "stack": [
      "middleware",
      "wrappedController"
    ]
  },
  {
    "name": null,
    "methods": [
      "POST"
    ],
    "paramNames": [],
    "path": "/admin/banner/sort",
    "regexp": "/^\\/admin\\/banner\\/sort(?:\\/(?=$))?$/",
    "stack": [
      "middleware",
      "wrappedController"
    ]
  },
  {
    "name": "s",
    "methods": [
      "HEAD",
      "GET"
    ],
    "paramNames": [],
    "path": "/admin/home_nav",
    "regexp": "/^\\/admin\\/home_nav(?:\\/(?=$))?$/",
    "stack": [
      "middleware",
      "wrappedController"
    ]
  },
  {
    "name": "s",
    "methods": [
      "POST"
    ],
    "paramNames": [],
    "path": "/admin/home_nav",
    "regexp": "/^\\/admin\\/home_nav(?:\\/(?=$))?$/",
    "stack": [
      "middleware",
      "wrappedController"
    ]
  },
  {
    "name": null,
    "methods": [
      "PATCH",
      "PUT"
    ],
    "paramNames": [
      {
        "name": "id",
        "prefix": "/",
        "delimiter": "/",
        "optional": false,
        "repeat": false,
        "partial": false,
        "asterisk": false,
        "pattern": "[^\\/]+?"
      }
    ],
    "path": "/admin/home_nav/:id",
    "regexp": "/^\\/admin\\/home_nav\\/((?:[^\\/]+?))(?:\\/(?=$))?$/",
    "stack": [
      "middleware",
      "wrappedController"
    ]
  },
  {
    "name": "destroy_",
    "methods": [
      "DELETE"
    ],
    "paramNames": [
      {
        "name": "id",
        "prefix": "/",
        "delimiter": "/",
        "optional": false,
        "repeat": false,
        "partial": false,
        "asterisk": false,
        "pattern": "[^\\/]+?"
      }
    ],
    "path": "/admin/home_nav/:id",
    "regexp": "/^\\/admin\\/home_nav\\/((?:[^\\/]+?))(?:\\/(?=$))?$/",
    "stack": [
      "middleware",
      "wrappedController"
    ]
  },
  {
    "name": null,
    "methods": [
      "DELETE"
    ],
    "paramNames": [],
    "path": "/admin/home_nav",
    "regexp": "/^\\/admin\\/home_nav(?:\\/(?=$))?$/",
    "stack": [
      "middleware",
      "wrappedController"
    ]
  },
  {
    "name": null,
    "methods": [
      "POST"
    ],
    "paramNames": [],
    "path": "/admin/home_nav/sort",
    "regexp": "/^\\/admin\\/home_nav\\/sort(?:\\/(?=$))?$/",
    "stack": [
      "middleware",
      "wrappedController"
    ]
  },
  {
    "name": null,
    "methods": [
      "HEAD",
      "GET"
    ],
    "paramNames": [],
    "path": "/admin/home_nav/data",
    "regexp": "/^\\/admin\\/home_nav\\/data(?:\\/(?=$))?$/",
    "stack": [
      "middleware",
      "wrappedController"
    ]
  },
  {
    "name": null,
    "methods": [
      "HEAD",
      "GET"
    ],
    "paramNames": [],
    "path": "/weapp/login",
    "regexp": "/^\\/weapp\\/login(?:\\/(?=$))?$/",
    "stack": [
      "wrappedController"
    ]
  },
  {
    "name": null,
    "methods": [
      "POST"
    ],
    "paramNames": [],
    "path": "/weapp/user/update",
    "regexp": "/^\\/weapp\\/user\\/update(?:\\/(?=$))?$/",
    "stack": [
      "middleware",
      "wrappedController"
    ]
  },
  {
    "name": null,
    "methods": [
      "HEAD",
      "GET"
    ],
    "paramNames": [],
    "path": "/weapp/banner",
    "regexp": "/^\\/weapp\\/banner(?:\\/(?=$))?$/",
    "stack": [
      "wrappedController"
    ]
  },
  {
    "name": null,
    "methods": [
      "HEAD",
      "GET"
    ],
    "paramNames": [],
    "path": "/weapp/home_nav",
    "regexp": "/^\\/weapp\\/home_nav(?:\\/(?=$))?$/",
    "stack": [
      "wrappedController"
    ]
  },
  {
    "name": null,
    "methods": [
      "HEAD",
      "GET"
    ],
    "paramNames": [],
    "path": "/weapp/recommend",
    "regexp": "/^\\/weapp\\/recommend(?:\\/(?=$))?$/",
    "stack": [
      "wrappedController"
    ]
  },
  {
    "name": null,
    "methods": [
      "HEAD",
      "GET"
    ],
    "paramNames": [],
    "path": "/weapp/category",
    "regexp": "/^\\/weapp\\/category(?:\\/(?=$))?$/",
    "stack": [
      "wrappedController"
    ]
  }
]